owon_psu/__init__.py
owon_psu-0.0.5.dist-info/licenses/LICENSE
owon_psu-0.0.5.dist-info/METADATA
owon_psu-0.0.5.dist-info/WHEEL
owon_psu-0.0.5.dist-info/top_level.txt
owon_psu-0.0.5.dist-info/RECORD
