Metadata-Version: 2.4
Name: owon_psu
Version: 0.0.5
Summary: Simple Python library for controlling Owon SPE6103 and SPE3103 power supplies
Home-page: https://github.com/robbederks/owon-psu-control
Author: Robbe Derks
Author-email: robbe.derks@gmail.com
Project-URL: Source Code, https://github.com/robbederks/owon-psu-control
Project-URL: Bug Tracker, https://github.com/robbederks/owon-psu-control/issues
Keywords: scpi,owon,SPE6103,SPE3103,simple
Classifier: Programming Language :: Python :: 3
Classifier: License :: OSI Approved :: MIT License
Classifier: Operating System :: OS Independent
Classifier: Development Status :: 4 - Beta
License-File: LICENSE
Requires-Dist: pyserial
Dynamic: author
Dynamic: author-email
Dynamic: classifier
Dynamic: description
Dynamic: description-content-type
Dynamic: home-page
Dynamic: keywords
Dynamic: license-file
Dynamic: project-url
Dynamic: requires-dist
Dynamic: summary
